Workbook

Sheet summary
A1: Group | B1: File | C1: Year | D1: Tactic | E1: Tool | F1: TP | G1: TN | H1: FP | I1: FN | J1: TOTAL | K1: Precision | L1: Accuracy | M1: Recall Ratio | N1: Notes
A2: Control A | B2: Alexa | C2: 2017 | D2: Web Services | E2: Shannon Entropy | F2: =COUNTIFS('con-a_alexa'!B:B,"evil",'con-a_alexa'!D:D,"suspicious") -> 0 | G2: =COUNTIFS('con-a_alexa'!B:B,"benign",'con-a_alexa'!D:D,"normal") -> 2885 | H2: =COUNTIFS('con-a_alexa'!B:B,"benign",'con-a_alexa'!D:D,"suspicious") -> 115 | I2: =COUNTIFS('con-a_alexa'!B:B,"evil",'con-a_alexa'!D:D,"normal") -> 0 | J2: =SUM(F2:I2) -> 3000 | K2: =F2/(F2+H2) -> 0 | L2: =(F2+G2)/(J2) -> 0.96166667 | M2: =(F2/(F2+I2)) -> #DIV/0!
A3: Control A | B3: Alexa | C3: 2017 | D3: Web Services | E3: Exp0se | F3: =COUNTIFS('con-a_alexa'!B:B,"evil",'con-a_alexa'!E:E,"TRUE") -> 0 | G3: =COUNTIFS('con-a_alexa'!B:B,"benign",'con-a_alexa'!E:E,"FALSE") -> 1598 | H3: =COUNTIFS('con-a_alexa'!B:B,"benign",'con-a_alexa'!E:E,"TRUE") -> 1402 | I3: =COUNTIFS('con-a_alexa'!B:B,"evil",'con-a_alexa'!E:E,"FALSE") -> 0 | J3: =SUM(F3:I3) -> 3000 | K3: =F3/(F3+H3) -> 0 | L3: =(F3+G3)/(J3) -> 0.53266667 | M3: =(F3/(F3+I3)) -> #DIV/0!
A4: Control A | B4: Alexa | C4: 2017 | D4: Web Services | E4: Mia | F4: =COUNTIFS('con-a_alexa'!B:B,"evil",'con-a_alexa'!F:F,"dga") -> 0 | G4: =COUNTIFS('con-a_alexa'!B:B,"benign",'con-a_alexa'!F:F,"legit") -> 2961 | H4: =COUNTIFS('con-a_alexa'!B:B,"benign",'con-a_alexa'!F:F,"dga") -> 39 | I4: =COUNTIFS('con-a_alexa'!B:B,"evil",'con-a_alexa'!F:F,"legit") -> 0 | J4: =SUM(F4:I4) -> 3000 | K4: =F4/(F4+H4) -> 0 | L4: =(F4+G4)/(J4) -> 0.987 | M4: =(F4/(F4+I4)) -> #DIV/0!
A5: Control A | B5: Alexa | C5: 2017 | D5: Web Services | E5: DGAD | F5: =COUNTIFS('con-a_alexa'!B:B,"evil",'con-a_alexa'!G:G,"TRUE") -> 0 | G5: =COUNTIFS('con-a_alexa'!B:B,"benign",'con-a_alexa'!G:G,"FALSE") -> 2903 | H5: =COUNTIFS('con-a_alexa'!B:B,"benign",'con-a_alexa'!G:G,"TRUE") -> 97 | I5: =COUNTIFS('con-a_alexa'!B:B,"evil",'con-a_alexa'!G:G,"FALSE") -> 0 | J5: =SUM(F5:I5) -> 3000 | K5: =F5/(F5+H5) -> 0 | L5: =(F5+G5)/(J5) -> 0.96766667 | M5: =(F5/(F5+I5)) -> #DIV/0!
A6: Control B | B6: Cisco | C6: 2025 | D6: Internet Services | E6: Shannon Entropy | F6: =COUNTIFS('con-b_cisco'!B:B,"evil",'con-b_cisco'!D:D,"suspicious") -> 0 | G6: =COUNTIFS('con-b_cisco'!B:B,"benign",'con-b_cisco'!D:D,"normal") -> 2875 | H6: =COUNTIFS('con-b_cisco'!B:B,"benign",'con-b_cisco'!D:D,"suspicious") -> 125 | I6: =COUNTIFS('con-b_cisco'!B:B,"evil",'con-b_cisco'!D:D,"normal") -> 0 | J6: =SUM(F6:I6) -> 3000 | K6: =F6/(F6+H6) -> 0 | L6: =(F6+G6)/(J6) -> 0.95833333 | M6: =(F6/(F6+I6)) -> #DIV/0!
A7: Control B | B7: Cisco | C7: 2025 | D7: Internet Services | E7: Exp0se | F7: =COUNTIFS('con-b_cisco'!B:B,"evil",'con-b_cisco'!E:E,"TRUE") -> 0 | G7: =COUNTIFS('con-b_cisco'!B:B,"benign",'con-b_cisco'!E:E,"FALSE") -> 2462 | H7: =COUNTIFS('con-b_cisco'!B:B,"benign",'con-b_cisco'!E:E,"TRUE") -> 538 | I7: =COUNTIFS('con-b_cisco'!B:B,"evil",'con-b_cisco'!E:E,"FALSE") -> 0 | J7: =SUM(F7:I7) -> 3000 | K7: =F7/(F7+H7) -> 0 | L7: =(F7+G7)/(J7) -> 0.82066667 | M7: =(F7/(F7+I7)) -> #DIV/0!
A8: Control B | B8: Cisco | C8: 2025 | D8: Internet Services | E8: Mia | F8: =COUNTIFS('con-b_cisco'!B:B,"evil",'con-b_cisco'!F:F,"dga") -> 0 | G8: =COUNTIFS('con-b_cisco'!B:B,"benign",'con-b_cisco'!F:F,"legit") -> 2741 | H8: =COUNTIFS('con-b_cisco'!B:B,"benign",'con-b_cisco'!F:F,"dga") -> 259 | I8: =COUNTIFS('con-b_cisco'!B:B,"evil",'con-b_cisco'!F:F,"legit") -> 0 | J8: =SUM(F8:I8) -> 3000 | K8: =F8/(F8+H8) -> 0 | L8: =(F8+G8)/(J8) -> 0.91366667 | M8: =(F8/(F8+I8)) -> #DIV/0!
A9: Control B | B9: Cisco | C9: 2025 | D9: Internet Services | E9: DGAD | F9: =COUNTIFS('con-b_cisco'!B:B,"evil",'con-b_cisco'!G:G,"TRUE") -> 0 | G9: =COUNTIFS('con-b_cisco'!B:B,"benign",'con-b_cisco'!G:G,"FALSE") -> 2726 | H9: =COUNTIFS('con-b_cisco'!B:B,"benign",'con-b_cisco'!G:G,"TRUE") -> 269 | I9: =COUNTIFS('con-b_cisco'!B:B,"evil",'con-b_cisco'!G:G,"FALSE")+COUNTIFS('con-b_cisco'!B:B,"benign",'con-b_cisco'!G:G,"N/A") -> 5 | J9: =SUM(F9:I9) -> 3000 | K9: =F9/(F9+H9) -> 0 | L9: =(F9+G9)/(J9) -> 0.90866667 | M9: =(F9/(F9+I9)) -> 0 | N9: 5x domains skipped due to character limit (considered a missed untested threat)
A10: Control C | B10: Cloudflare | C10: 2025 | D10: Global Services | E10: Shannon Entropy | F10: =COUNTIFS('con-c_cloudflare'!B:B,"evil",'con-c_cloudflare'!D:D,"suspicious") -> 0 | G10: =COUNTIFS('con-c_cloudflare'!B:B,"benign",'con-c_cloudflare'!D:D,"normal") -> 2888 | H10: =COUNTIFS('con-c_cloudflare'!B:B,"benign",'con-c_cloudflare'!D:D,"suspicious") -> 112 | I10: =COUNTIFS('con-c_cloudflare'!B:B,"evil",'con-c_cloudflare'!D:D,"normal") -> 0 | J10: =SUM(F10:I10) -> 3000 | K10: =F10/(F10+H10) -> 0 | L10: =(F10+G10)/(J10) -> 0.96266667 | M10: =(F10/(F10+I10)) -> #DIV/0!
A11: Control C | B11: Cloudflare | C11: 2025 | D11: Global Services | E11: Exp0se | F11: =COUNTIFS('con-c_cloudflare'!B:B,"evil",'con-c_cloudflare'!E:E,"TRUE") -> 0 | G11: =COUNTIFS('con-c_cloudflare'!B:B,"benign",'con-c_cloudflare'!E:E,"FALSE") -> 2520 | H11: =COUNTIFS('con-c_cloudflare'!B:B,"benign",'con-c_cloudflare'!E:E,"TRUE") -> 480 | I11: =COUNTIFS('con-c_cloudflare'!B:B,"evil",'con-c_cloudflare'!E:E,"FALSE") -> 0 | J11: =SUM(F11:I11) -> 3000 | K11: =F11/(F11+H11) -> 0 | L11: =(F11+G11)/(J11) -> 0.84 | M11: =(F11/(F11+I11)) -> #DIV/0!
A12: Control C | B12: Cloudflare | C12: 2025 | D12: Global Services | E12: Mia | F12: =COUNTIFS('con-c_cloudflare'!B:B,"evil",'con-c_cloudflare'!F:F,"dga") -> 0 | G12: =COUNTIFS('con-c_cloudflare'!B:B,"benign",'con-c_cloudflare'!F:F,"legit") -> 2952 | H12: =COUNTIFS('con-c_cloudflare'!B:B,"benign",'con-c_cloudflare'!F:F,"dga") -> 48 | I12: =COUNTIFS('con-c_cloudflare'!B:B,"evil",'con-c_cloudflare'!F:F,"legit") -> 0 | J12: =SUM(F12:I12) -> 3000 | K12: =F12/(F12+H12) -> 0 | L12: =(F12+G12)/(J12) -> 0.984 | M12: =(F12/(F12+I12)) -> #DIV/0!
A13: Control C | B13: Cloudflare | C13: 2025 | D13: Global Services | E13: DGAD | F13: =COUNTIFS('con-c_cloudflare'!B:B,"evil",'con-c_cloudflare'!G:G,"TRUE") -> 0 | G13: =COUNTIFS('con-c_cloudflare'!B:B,"benign",'con-c_cloudflare'!G:G,"FALSE") -> 2786 | H13: =COUNTIFS('con-c_cloudflare'!B:B,"benign",'con-c_cloudflare'!G:G,"TRUE") -> 214 | I13: =COUNTIFS('con-c_cloudflare'!B:B,"evil",'con-c_cloudflare'!G:G,"FALSE") -> 0 | J13: =SUM(F13:I13) -> 3000 | K13: =F13/(F13+H13) -> 0 | L13: =(F13+G13)/(J13) -> 0.92866667 | M13: =(F13/(F13+I13)) -> #DIV/0!
A14: Control D | B14: Majestic | C14: 2025 | D14: UK Services | E14: Shannon Entropy | F14: =COUNTIFS('con-d_majestic'!B:B,"evil",'con-d_majestic'!D:D,"suspicious") -> 0 | G14: =COUNTIFS('con-d_majestic'!B:B,"benign",'con-d_majestic'!D:D,"normal") -> 2874 | H14: =COUNTIFS('con-d_majestic'!B:B,"benign",'con-d_majestic'!D:D,"suspicious") -> 126 | I14: =COUNTIFS('con-d_majestic'!B:B,"evil",'con-d_majestic'!D:D,"normal") -> 0 | J14: =SUM(F14:I14) -> 3000 | K14: =F14/(F14+H14) -> 0 | L14: =(F14+G14)/(J14) -> 0.958 | M14: =(F14/(F14+I14)) -> #DIV/0!
A15: Control D | B15: Majestic | C15: 2025 | D15: UK Services | E15: Exp0se | F15: =COUNTIFS('con-d_majestic'!B:B,"evil",'con-d_majestic'!E:E,"TRUE") -> 0 | G15: =COUNTIFS('con-d_majestic'!B:B,"benign",'con-d_majestic'!E:E,"FALSE") -> 2407 | H15: =COUNTIFS('con-d_majestic'!B:B,"benign",'con-d_majestic'!E:E,"TRUE") -> 592 | I15: =COUNTIFS('con-d_majestic'!B:B,"evil",'con-d_majestic'!E:E,"FALSE")+COUNTIFS('con-d_majestic'!B:B,"benign",'con-d_majestic'!E:E,"N/A") -> 1 | J15: =SUM(F15:I15) -> 3000 | K15: =F15/(F15+H15) -> 0 | L15: =(F15+G15)/(J15) -> 0.80233333 | M15: =(F15/(F15+I15)) -> 0 | N15: 1x domain skipped due was too short for exp0se to process.
A16: Control D | B16: Majestic | C16: 2025 | D16: UK Services | E16: Mia | F16: =COUNTIFS('con-d_majestic'!B:B,"evil",'con-d_majestic'!F:F,"dga") -> 0 | G16: =COUNTIFS('con-d_majestic'!B:B,"benign",'con-d_majestic'!F:F,"legit") -> 2944 | H16: =COUNTIFS('con-d_majestic'!B:B,"benign",'con-d_majestic'!F:F,"dga") -> 56 | I16: =COUNTIFS('con-d_majestic'!B:B,"evil",'con-d_majestic'!F:F,"legit") -> 0 | J16: =SUM(F16:I16) -> 3000 | K16: =F16/(F16+H16) -> 0 | L16: =(F16+G16)/(J16) -> 0.98133333 | M16: =(F16/(F16+I16)) -> #DIV/0!
A17: Control D | B17: Majestic | C17: 2025 | D17: UK Services | E17: DGAD | F17: =COUNTIFS('con-d_majestic'!B:B,"evil",'con-d_majestic'!G:G,"TRUE") -> 0 | G17: =COUNTIFS('con-d_majestic'!B:B,"benign",'con-d_majestic'!G:G,"FALSE") -> 2628 | H17: =COUNTIFS('con-d_majestic'!B:B,"benign",'con-d_majestic'!G:G,"TRUE") -> 372 | I17: =COUNTIFS('con-d_majestic'!B:B,"evil",'con-d_majestic'!G:G,"FALSE") -> 0 | J17: =SUM(F17:I17) -> 3000 | K17: =F17/(F17+H17) -> 0 | L17: =(F17+G17)/(J17) -> 0.876 | M17: =(F17/(F17+I17)) -> #DIV/0!
A18: Experimental A | B18: Cats Cradle | C18: 2022 | D18: Randomized Characters | E18: Shannon Entropy | F18: =COUNTIFS('ex-a_cats'!B:B,"evil",'ex-a_cats'!D:D,"suspicious") -> 151 | G18: =COUNTIFS('ex-a_cats'!B:B,"benign",'ex-a_cats'!D:D,"normal") -> 0 | H18: =COUNTIFS('ex-a_cats'!B:B,"benign",'ex-a_cats'!D:D,"suspicious") -> 0 | I18: =COUNTIFS('ex-a_cats'!B:B,"evil",'ex-a_cats'!D:D,"normal") -> 2849 | J18: =SUM(F18:I18) -> 3000 | K18: =F18/(F18+H18) -> 1 | L18: =(F18+G18)/(J18) -> 0.050333333 | M18: =(F18/(F18+I18)) -> 0.050333333
A19: Experimental A | B19: Cats Cradle | C19: 2022 | D19: Randomized Characters | E19: Exp0se | F19: =COUNTIFS('ex-a_cats'!B:B,"evil",'ex-a_cats'!E:E,"TRUE") -> 2752 | G19: =COUNTIFS('ex-a_cats'!B:B,"benign",'ex-a_cats'!E:E,"FALSE") -> 0 | H19: =COUNTIFS('ex-a_cats'!B:B,"benign",'ex-a_cats'!E:E,"TRUE") -> 0 | I19: =COUNTIFS('ex-a_cats'!B:B,"evil",'ex-a_cats'!E:E,"FALSE") -> 248 | J19: =SUM(F19:I19) -> 3000 | K19: =F19/(F19+H19) -> 1 | L19: =(F19+G19)/(J19) -> 0.91733333 | M19: =(F19/(F19+I19)) -> 0.91733333
A20: Experimental A | B20: Cats Cradle | C20: 2022 | D20: Randomized Characters | E20: Mia | F20: =COUNTIFS('ex-a_cats'!B:B,"evil",'ex-a_cats'!F:F,"dga") -> 5 | G20: =COUNTIFS('ex-a_cats'!B:B,"benign",'ex-a_cats'!F:F,"legit") -> 0 | H20: =COUNTIFS('ex-a_cats'!B:B,"benign",'ex-a_cats'!F:F,"dga") -> 0 | I20: =COUNTIFS('ex-a_cats'!B:B,"evil",'ex-a_cats'!F:F,"legit") -> 2995 | J20: =SUM(F20:I20) -> 3000 | K20: =F20/(F20+H20) -> 1 | L20: =(F20+G20)/(J20) -> 0.0016666667 | M20: =(F20/(F20+I20)) -> 0.0016666667
A21: Experimental A | B21: Cats Cradle | C21: 2022 | D21: Randomized Characters | E21: DGAD | F21: =COUNTIFS('ex-a_cats'!B:B,"evil",'ex-a_cats'!G:G,"TRUE") -> 2735 | G21: =COUNTIFS('ex-a_cats'!B:B,"benign",'ex-a_cats'!G:G,"FALSE") -> 0 | H21: =COUNTIFS('ex-a_cats'!B:B,"benign",'ex-a_cats'!G:G,"TRUE") -> 0 | I21: =COUNTIFS('ex-a_cats'!B:B,"evil",'ex-a_cats'!G:G,"FALSE") -> 265 | J21: =SUM(F21:I21) -> 3000 | K21: =F21/(F21+H21) -> 1 | L21: =(F21+G21)/(J21) -> 0.91166667 | M21: =(F21/(F21+I21)) -> 0.91166667
A22: Experimental B | B22: Double Helix | C22: 2023 | D22: Dictionary Word Concatenation (English) | E22: Shannon Entropy | F22: =COUNTIFS('ex-b_double'!B:B,"evil",'ex-b_double'!D:D,"suspicious") -> 21 | G22: =COUNTIFS('ex-b_double'!B:B,"benign",'ex-b_double'!D:D,"normal") -> 0 | H22: =COUNTIFS('ex-b_double'!B:B,"benign",'ex-b_double'!D:D,"suspicious") -> 0 | I22: =COUNTIFS('ex-b_double'!B:B,"evil",'ex-b_double'!D:D,"normal") -> 2979 | J22: =SUM(F22:I22) -> 3000 | K22: =F22/(F22+H22) -> 1 | L22: =(F22+G22)/(J22) -> 0.007 | M22: =(F22/(F22+I22)) -> 0.007
A23: Experimental B | B23: Double Helix | C23: 2023 | D23: Dictionary Word Concatenation (English) | E23: Exp0se | F23: =COUNTIFS('ex-b_double'!B:B,"evil",'ex-b_double'!E:E,"TRUE") -> 44 | G23: =COUNTIFS('ex-b_double'!B:B,"benign",'ex-b_double'!E:E,"FALSE") -> 0 | H23: =COUNTIFS('ex-b_double'!B:B,"benign",'ex-b_double'!E:E,"TRUE") -> 0 | I23: =COUNTIFS('ex-b_double'!B:B,"evil",'ex-b_double'!E:E,"FALSE") -> 2956 | J23: =SUM(F23:I23) -> 3000 | K23: =F23/(F23+H23) -> 1 | L23: =(F23+G23)/(J23) -> 0.014666667 | M23: =(F23/(F23+I23)) -> 0.014666667
A24: Experimental B | B24: Double Helix | C24: 2023 | D24: Dictionary Word Concatenation (English) | E24: Mia | F24: =COUNTIFS('ex-b_double'!B:B,"evil",'ex-b_double'!F:F,"dga") -> 12 | G24: =COUNTIFS('ex-b_double'!B:B,"benign",'ex-b_double'!F:F,"legit") -> 0 | H24: =COUNTIFS('ex-b_double'!B:B,"benign",'ex-b_double'!F:F,"dga") -> 0 | I24: =COUNTIFS('ex-b_double'!B:B,"evil",'ex-b_double'!F:F,"legit") -> 2988 | J24: =SUM(F24:I24) -> 3000 | K24: =F24/(F24+H24) -> 1 | L24: =(F24+G24)/(J24) -> 0.004 | M24: =(F24/(F24+I24)) -> 0.004
A25: Experimental B | B25: Double Helix | C25: 2023 | D25: Dictionary Word Concatenation (English) | E25: DGAD | F25: =COUNTIFS('ex-b_double'!B:B,"evil",'ex-b_double'!G:G,"TRUE") -> 133 | G25: =COUNTIFS('ex-b_double'!B:B,"benign",'ex-b_double'!G:G,"FALSE") -> 0 | H25: =COUNTIFS('ex-b_double'!B:B,"benign",'ex-b_double'!G:G,"TRUE") -> 0 | I25: =COUNTIFS('ex-b_double'!B:B,"evil",'ex-b_double'!G:G,"FALSE") -> 2867 | J25: =SUM(F25:I25) -> 3000 | K25: =F25/(F25+H25) -> 1 | L25: =(F25+G25)/(J25) -> 0.044333333 | M25: =(F25/(F25+I25)) -> 0.044333333
A26: Experimental C | B26: Pandoras Box | C26: 2024 | D26: Combo-squatting w/ keywords (Typo-squatting) | E26: Shannon Entropy | F26: =COUNTIFS('ex-c_pandora'!B:B,"evil",'ex-c_pandora'!D:D,"suspicious") -> 206 | G26: =COUNTIFS('ex-c_pandora'!B:B,"benign",'ex-c_pandora'!D:D,"normal") -> 0 | H26: =COUNTIFS('ex-c_pandora'!B:B,"benign",'ex-c_pandora'!D:D,"suspicious") -> 0 | I26: =COUNTIFS('ex-c_pandora'!B:B,"evil",'ex-c_pandora'!D:D,"normal") -> 2794 | J26: =SUM(F26:I26) -> 3000 | K26: =F26/(F26+H26) -> 1 | L26: =(F26+G26)/(J26) -> 0.068666667 | M26: =(F26/(F26+I26)) -> 0.068666667
A27: Experimental C | B27: Pandoras Box | C27: 2024 | D27: Combo-squatting w/ keywords (Typo-squatting) | E27: Exp0se | F27: =COUNTIFS('ex-c_pandora'!B:B,"evil",'ex-c_pandora'!E:E,"TRUE") -> 1195 | G27: =COUNTIFS('ex-c_pandora'!B:B,"benign",'ex-c_pandora'!E:E,"FALSE") -> 0 | H27: =COUNTIFS('ex-c_pandora'!B:B,"benign",'ex-c_pandora'!E:E,"TRUE") -> 0 | I27: =COUNTIFS('ex-c_pandora'!B:B,"evil",'ex-c_pandora'!E:E,"FALSE") -> 1805 | J27: =SUM(F27:I27) -> 3000 | K27: =F27/(F27+H27) -> 1 | L27: =(F27+G27)/(J27) -> 0.39833333 | M27: =(F27/(F27+I27)) -> 0.39833333
A28: Experimental C | B28: Pandoras Box | C28: 2024 | D28: Combo-squatting w/ keywords (Typo-squatting) | E28: Mia | F28: =COUNTIFS('ex-c_pandora'!B:B,"evil",'ex-c_pandora'!F:F,"dga") -> 191 | G28: =COUNTIFS('ex-c_pandora'!B:B,"benign",'ex-c_pandora'!F:F,"legit") -> 0 | H28: =COUNTIFS('ex-c_pandora'!B:B,"benign",'ex-c_pandora'!F:F,"dga") -> 0 | I28: =COUNTIFS('ex-c_pandora'!B:B,"evil",'ex-c_pandora'!F:F,"legit") -> 2809 | J28: =SUM(F28:I28) -> 3000 | K28: =F28/(F28+H28) -> 1 | L28: =(F28+G28)/(J28) -> 0.063666667 | M28: =(F28/(F28+I28)) -> 0.063666667
A29: Experimental C | B29: Pandoras Box | C29: 2024 | D29: Combo-squatting w/ keywords (Typo-squatting) | E29: DGAD | F29: =COUNTIFS('ex-c_pandora'!B:B,"evil",'ex-c_pandora'!G:G,"TRUE") -> 5 | G29: =COUNTIFS('ex-c_pandora'!B:B,"benign",'ex-c_pandora'!G:G,"FALSE") -> 0 | H29: =COUNTIFS('ex-c_pandora'!B:B,"benign",'ex-c_pandora'!G:G,"TRUE") -> 0 | I29: =COUNTIFS('ex-c_pandora'!B:B,"evil",'ex-c_pandora'!G:G,"FALSE") -> 2995 | J29: =SUM(F29:I29) -> 3000 | K29: =F29/(F29+H29) -> 1 | L29: =(F29+G29)/(J29) -> 0.0016666667 | M29: =(F29/(F29+I29)) -> 0.0016666667
A30: Experimental D | B30: Easy Rider | C30: 2025 | D30: Combo-squatting w/ partial randomized (Typo-squatting) | E30: Shannon Entropy | F30: =COUNTIFS('ex-d_easy'!B:B,"evil",'ex-d_easy'!D:D,"suspicious") -> 5 | G30: =COUNTIFS('ex-d_easy'!B:B,"benign",'ex-d_easy'!D:D,"normal") -> 0 | H30: =COUNTIFS('ex-d_easy'!B:B,"benign",'ex-d_easy'!D:D,"suspicious") -> 0 | I30: =COUNTIFS('ex-d_easy'!B:B,"evil",'ex-d_easy'!D:D,"normal") -> 2995 | J30: =SUM(F30:I30) -> 3000 | K30: =F30/(F30+H30) -> 1 | L30: =(F30+G30)/(J30) -> 0.0016666667 | M30: =(F30/(F30+I30)) -> 0.0016666667
A31: Experimental D | B31: Easy Rider | C31: 2025 | D31: Combo-squatting w/ partial randomized (Typo-squatting) | E31: Exp0se | F31: =COUNTIFS('ex-d_easy'!B:B,"evil",'ex-d_easy'!E:E,"TRUE") -> 1402 | G31: =COUNTIFS('ex-d_easy'!B:B,"benign",'ex-d_easy'!E:E,"FALSE") -> 0 | H31: =COUNTIFS('ex-d_easy'!B:B,"benign",'ex-d_easy'!E:E,"TRUE") -> 0 | I31: =COUNTIFS('ex-d_easy'!B:B,"evil",'ex-d_easy'!E:E,"FALSE") -> 1598 | J31: =SUM(F31:I31) -> 3000 | K31: =F31/(F31+H31) -> 1 | L31: =(F31+G31)/(J31) -> 0.46733333 | M31: =(F31/(F31+I31)) -> 0.46733333
A32: Experimental D | B32: Easy Rider | C32: 2025 | D32: Combo-squatting w/ partial randomized (Typo-squatting) | E32: Mia | F32: =COUNTIFS('ex-d_easy'!B:B,"evil",'ex-d_easy'!F:F,"dga") -> 325 | G32: =COUNTIFS('ex-d_easy'!B:B,"benign",'ex-d_easy'!F:F,"legit") -> 0 | H32: =COUNTIFS('ex-d_easy'!B:B,"benign",'ex-d_easy'!F:F,"dga") -> 0 | I32: =COUNTIFS('ex-d_easy'!B:B,"evil",'ex-d_easy'!F:F,"legit") -> 2675 | J32: =SUM(F32:I32) -> 3000 | K32: =F32/(F32+H32) -> 1 | L32: =(F32+G32)/(J32) -> 0.10833333 | M32: =(F32/(F32+I32)) -> 0.10833333
A33: Experimental D | B33: Easy Rider | C33: 2025 | D33: Combo-squatting w/ partial randomized (Typo-squatting) | E33: DGAD | F33: =COUNTIFS('ex-d_easy'!B:B,"evil",'ex-d_easy'!G:G,"TRUE") -> 18 | G33: =COUNTIFS('ex-d_easy'!B:B,"benign",'ex-d_easy'!G:G,"FALSE") -> 0 | H33: =COUNTIFS('ex-d_easy'!B:B,"benign",'ex-d_easy'!G:G,"TRUE") -> 0 | I33: =COUNTIFS('ex-d_easy'!B:B,"evil",'ex-d_easy'!G:G,"FALSE") -> 2982 | J33: =SUM(F33:I33) -> 3000 | K33: =F33/(F33+H33) -> 1 | L33: =(F33+G33)/(J33) -> 0.006 | M33: =(F33/(F33+I33)) -> 0.006

Sheet key
A1: Compare 1st Label vs Tool | B1: Definition | C1: Shannon | D1: Exp0se | E1: Mia | F1: DGAD
A2: TP | B2: Correct Detection | C2: Detected "evil" as "suspicious" | D2: Detected "evil" as "is_DGA:TRUE" | E2: Detected "evil" as "dga" | F2: Detected "evil" as "is_DGA:TRUE"
A3: TN | B3: Correct Ignore | C3: Detected "benign" as "normal" | D3: Detected "benign" as "is_DGA:FALSE" | E3: Detected "benign" as "legit" | F3: Detected "benign" as "is_DGA:FALSE"
A4: FP | B4: False Alarm | C4: Detected "benign" as "suspicious" | D4: Detected "benign" as "is_DGA:TRUE" | E4: Detected "benign" as "dga" | F4: Detected "benign" as "is_DGA:TRUE"
A5: FN | B5: Missed Threat | C5: Detected "evil" as "normal" | D5: Detected "evil" as "is_DGA:FALSE" | E5: Detected "evil" as "legit" | F5: Detected "evil" as "is_DGA:FALSE"

Sheet con-a_alexa
A1: Domains | B1: Verdict | C1: Shannon_Entropy | D1: Shannon_Flag | E1: exp0se (is_dga) | F1: mia_prediction | G1: DGAD: overall flag (is_dga)
A2: 010lm.com | B2: benign | C2: 0.432253 | D2: normal | E2: FALSE | F2: legit | G2: FALSE
A3: 02022222222.com | B3: benign | C3: 0.352944 | D3: normal | E3: TRUE | F3: legit | G3: TRUE
A4: 060s.com | B4: benign | C4: 0.25873 | D4: normal | E4: TRUE | F4: legit | G4: FALSE
A5: 1001fonts.net | B5: benign | C5: 1.219711 | D5: normal | E5: TRUE | F5: legit | G5: FALSE
A6: 10086.cn | B6: benign | C6: 0.086398 | D6: normal | E6: TRUE | F6: legit | G6: FALSE
A7: 100run.com | B7: benign | C7: 0.699643 | D7: normal | E7: FALSE | F7: legit | G7: FALSE
A8: 1024sj.com | B8: benign | C8: 0.392526 | D8: normal | E8: TRUE | F8: legit | G8: FALSE
A9: 1024v3.org | B9: benign | C9: 0.20828 | D9: normal | E9: FALSE | F9: legit | G9: FALSE
A10: 10bis.co.il | B10: benign | C10: 0.693508 | D10: normal | E10: TRUE | F10: legit | G10: FALSE
A11: 115.com | B11: benign | C11: 0.128618 | D11: normal | E11: FALSE | F11: legit | G11: FALSE
A12: 123watchmovies.org | B12: benign | C12: 2.453427 | D12: normal | E12: TRUE | F12: legit | G12: FALSE
A13: 131u.com | B13: benign | C13: 0.29314 | D13: normal | E13: FALSE | F13: legit | G13: FALSE
... A3001: zysj.com.cn | B3001: benign | C3001: 0.435491 | D3001: normal | E3001: TRUE | F3001: legit | G3001: FALSE

Sheet con-b_cisco
A1: Domains | B1: Verdict | C1: Shannon_Entropy | D1: Shannon_Flag | E1: exp0se (is_dga) | F1: mia_prediction | G1: DGAD: overall flag (is_dga)
A2: 0.docs.google.com | B2: benign | C2: 1.365991 | D2: normal | E2: FALSE | F2: legit | G2: FALSE
A3: 00-cordc1.laurelhealth.com | B3: benign | C3: 2.759245 | D3: normal | E3: FALSE | F3: legit | G3: FALSE
A4: 01-usgovtexas-gcch.cosmic-gcch.office365.us | B4: benign | C4: 1.330341 | D4: normal | E4: FALSE | F4: legit | G4: FALSE
A5: 05efe2edfc6098a8dc4a449c8698ed640b837b5f.cws.conviva.com | B5: benign | C5: 1.457152 | D5: normal | E5: FALSE | F5: legit | G5: TRUE
A6: 0e62b92a956add6e1c3871b7f592616665e610f12c6468eaad9533ef50834bc.us-east-1.prod.service.minerva.devices.a2z.com | B6: benign | C6: 0.407472 | D6: normal | E6: FALSE | F6: dga | G6: FALSE
A7: 0ecba478.us-east-1.token.awswaf.com | B7: benign | C7: 1.133124 | D7: normal | E7: TRUE | F7: legit | G7: TRUE
A8: 1.uk.pool.ntp.org | B8: benign | C8: 0.63066 | D8: normal | E8: FALSE | F8: legit | G8: FALSE
A9: 10.courier-push-apple.com.akadns.net | B9: benign | C9: 1.371361 | D9: normal | E9: TRUE | F9: legit | G9: FALSE
A10: 10-sansvr.laurelhealth.com | B10: benign | C10: 2.759245 | D10: normal | E10: FALSE | F10: legit | G10: FALSE
A11: 122.2o7.net | B11: benign | C11: 0.344793 | D11: normal | E11: FALSE | F11: legit | G11: FALSE
A12: 1359549.fls.doubleclick.net | B12: benign | C12: 2.232711 | D12: normal | E12: FALSE | F12: legit | G12: FALSE
A13: 14895689.fls.doubleclick.net | B13: benign | C13: 2.232711 | D13: normal | E13: FALSE | F13: legit | G13: TRUE
... A1825: partition-cname-trouter.pub-ent-uswe-12.ic3-edf-trouter.westus-prod.cosmic.office.net | B1825: benign | C1825: 1.270401 | D1825: normal | E1825: FALSE | F1825: dga | G1825: FALSE
A1826: partition-cname-trouter-ic3-edf-trouter-service-trouter-1.d02-002.ic3-edf-trouter.01-germanywestcentral-prod.cosmic.office.net | B1826: benign | C1826: 1.270401 | D1826: normal | E1826: FALSE | F1826: dga | G1826: N/A
A1827: partition-cname-trouter-ic3-edf-trouter-service-trouter-1.d02-006.ic3-edf-trouter.01-northeurope-prod.cosmic.office.net | B1827: benign | C1827: 1.270401 | D1827: normal | E1827: FALSE | F1827: dga | G1827: FALSE
A1828: partition-cname-trouter-ic3-edf-trouter-service-trouter-1.d02-006.ic3-edf-trouter.01-southcentralus-prod.cosmic.office.net | B1828: benign | C1828: 1.270401 | D1828: normal | E1828: FALSE | F1828: dga | G1828: N/A
A1829: partition-cname-trouter-ic3-edf-trouter-service-trouter-1.d02-014.ic3-edf-trouter.01-germanywestcentral-prod.cosmic.office.net | B1829: benign | C1829: 1.270401 | D1829: normal | E1829: FALSE | F1829: dga | G1829: N/A
A1830: partition-cname-trouter-ic3-edf-trouter-service-trouter-1.d02-026.ic3-edf-trouter.01-eastus-prod.cosmic.office.net | B1830: benign | C1830: 1.270401 | D1830: normal | E1830: FALSE | F1830: dga | G1830: FALSE
A1831: partition-cname-trouter-ic3-edf-trouter-service-trouter-2.d02-028.ic3-edf-trouter.01-swedencentral-prod.cosmic.office.net | B1831: benign | C1831: 1.270401 | D1831: normal | E1831: FALSE | F1831: dga | G1831: N/A
A1832: partition-cname-trouter-ic3-edf-trouter-service-trouter-2.d02-030.ic3-edf-trouter.01-swedencentral-prod.cosmic.office.net | B1832: benign | C1832: 1.270401 | D1832: normal | E1832: FALSE | F1832: dga | G1832: N/A
A1833: partition-cname-trouter-ic3-edf-trouter-service-trouter-2.d02-041.ic3-edf-trouter.01-westeurope-prod.cosmic.office.net | B1833: benign | C1833: 1.270401 | D1833: normal | E1833: FALSE | F1833: dga | G1833: FALSE
A1834: partition-cname-trouter-ic3-edf-trouter-service-trouter-2.d02-055.ic3-edf-trouter.01-westus-prod.cosmic.office.net | B1834: benign | C1834: 1.270401 | D1834: normal | E1834: FALSE | F1834: dga | G1834: FALSE
A1835: partition-cname-trouter-ic3-edf-trouter-service-trouter-2.d02-075.ic3-edf-trouter.01-westeurope-prod.cosmic.office.net | B1835: benign | C1835: 1.270401 | D1835: normal | E1835: FALSE | F1835: dga | G1835: FALSE
A1836: partition-cname-trouter-ic3-edf-trouter-service-trouter-2.d02-483.ic3-edf-trouter.01-westus-prod.cosmic.office.net | B1836: benign | C1836: 1.270401 | D1836: normal | E1836: FALSE | F1836: dga | G1836: FALSE
A1837: partnerstack.com | B1837: benign | C1837: 2.844081 | D1837: normal | E1837: FALSE | F1837: legit | G1837: FALSE
A1838: pas.esports.rpg.riotgames.com | B1838: benign | C1838: 2.22531 | D1838: normal | E1838: FALSE | F1838: legit | G1838: FALSE
A1839: password.quicklaunch.io | B1839: benign | C1839: 2.005923 | D1839: normal | E1839: FALSE | F1839: legit | G1839: FALSE
A1840: pastelink.net | B1840: benign | C1840: 2.076669 | D1840: normal | E1840: FALSE | F1840: legit | G1840: FALSE
A1841: payments.playgami.scopely.com | B1841: benign | C1841: 1.497094 | D1841: normal | E1841: FALSE | F1841: legit | G1841: FALSE
A1842: payments.realms.minecraft-services.net | B1842: benign | C1842: 4.042172 | D1842: suspicious | E1842: FALSE | F1842: legit | G1842: FALSE
A1843: pb.dmxleo.com | B1843: benign | C1843: 1.193631 | D1843: normal | E1843: TRUE | F1843: legit | G1843: TRUE
A1844: pbs.ovhnextmillmedia.com | B1844: benign | C1844: 3.420995 | D1844: suspicious | E1844: FALSE | F1844: dga | G1844: FALSE
... A3001: zws4-1.web.telegram.org | B3001: benign | C3001: 1.94249 | D3001: normal | E3001: FALSE | F3001: legit | G3001: FALSE

Sheet con-c_cloudflare
A1: Domains | B1: Verdict | C1: Shannon_Entropy | D1: Shannon_Flag | E1: exp0se (is_dga) | F1: mia_prediction | G1: DGAD: overall flag (is_dga)
A2: 0ts7e3.cn | B2: benign | C2: 0.840736 | D2: normal | E2: FALSE | F2: legit | G2: FALSE
A3: 11880.com | B3: benign | C3: 0.140967 | D3: normal | E3: FALSE | F3: legit | G3: FALSE
A4: 123av.com | B4: benign | C4: 0.500958 | D4: normal | E4: FALSE | F4: legit | G4: FALSE
A5: 123rf.com | B5: benign | C5: 0.456674 | D5: normal | E5: FALSE | F5: legit | G5: FALSE
A6: 12880.com | B6: benign | C6: 0.126034 | D6: normal | E6: FALSE | F6: legit | G6: FALSE
A7: 16hlbg.cn | B7: benign | C7: 0.659041 | D7: normal | E7: TRUE | F7: legit | G7: FALSE
A8: 18374938.com | B8: benign | C8: 0.185323 | D8: normal | E8: FALSE | F8: legit | G8: TRUE
A9: 18av.mov | B9: benign | C9: 0.454371 | D9: normal | E9: FALSE | F9: legit | G9: FALSE
A10: 1home.io | B10: benign | C10: 0.969011 | D10: normal | E10: FALSE | F10: legit | G10: FALSE
A11: 1prime.ru | B11: benign | C11: 1.211518 | D11: normal | E11: FALSE | F11: legit | G11: FALSE
A12: 1v9.gg | B12: benign | C12: 0.145818 | D12: normal | E12: FALSE | F12: legit | G12: FALSE
A13: 1worldsync.com | B13: benign | C13: 1.815463 | D13: normal | E13: FALSE | F13: legit | G13: FALSE
... A3001: zyrosite.com | B3001: benign | C3001: 1.7581 | D3001: normal | E3001: FALSE | F3001: legit | G3001: FALSE

Sheet con-d_majestic
A1: Domains | B1: Verdict | C1: Shannon_Entropy | D1: Shannon_Flag | E1: exp0se (is_dga) | F1: mia_prediction | G1: DGAD: overall flag (is_dga)
A2: 0005554tz1.info | B2: benign | C2: 0.430977 | D2: normal | E2: TRUE | F2: legit | G2: TRUE
A3: 0854jx.com | B3: benign | C3: 0.138001 | D3: normal | E3: TRUE | F3: legit | G3: FALSE
A4: 0dwf9e.cn | B4: benign | C4: 0.681284 | D4: normal | E4: TRUE | F4: legit | G4: FALSE
A5: 0mso6.com | B5: benign | C5: 0.727027 | D5: normal | E5: FALSE | F5: legit | G5: FALSE
A6: 0p40y.com | B6: benign | C6: 0.263079 | D6: normal | E6: TRUE | F6: legit | G6: FALSE
A7: 0q246.com | B7: benign | C7: 0.104175 | D7: normal | E7: FALSE | F7: legit | G7: FALSE
A8: 0s08w.com | B8: benign | C8: 0.345598 | D8: normal | E8: TRUE | F8: legit | G8: FALSE
A9: 0ys0i.com | B9: benign | C9: 0.607683 | D9: normal | E9: FALSE | F9: legit | G9: FALSE
A10: 10to8.com | B10: benign | C10: 0.601226 | D10: normal | E10: FALSE | F10: legit | G10: FALSE
A11: 123-reg.co.uk | B11: benign | C11: 0.849995 | D11: normal | E11: FALSE | F11: legit | G11: FALSE
A12: 123rf.com | B12: benign | C12: 0.456674 | D12: normal | E12: FALSE | F12: legit | G12: FALSE
A13: 12gobiking.nl | B13: benign | C13: 1.661403 | D13: normal | E13: FALSE | F13: legit | G13: FALSE
... A869: eppli.com | B869: benign | C869: 1.085792 | D869: normal | E869: FALSE | F869: legit | G869: FALSE
A870: eps.kz | B870: benign | C870: 0.710679 | D870: normal | E870: N/A | F870: legit | G870: FALSE
A871: epsontario.com | B871: benign | C871: 2.595268 | D871: normal | E871: FALSE | F871: legit | G871: FALSE
A872: eqbmmf.cn | B872: benign | C872: 0.930265 | D872: normal | E872: TRUE | F872: legit | G872: TRUE
A873: eqmxyk.cn | B873: benign | C873: 0.774295 | D873: normal | E873: TRUE | F873: legit | G873: TRUE
A874: equalizersoccer.com | B874: benign | C874: 3.404207 | D874: normal | E874: FALSE | F874: legit | G874: FALSE
A875: erau.edu | B875: benign | C875: 1.033418 | D875: normal | E875: FALSE | F875: legit | G875: FALSE
A876: ericaalvarez.top | B876: benign | C876: 2.854588 | D876: normal | E876: FALSE | F876: legit | G876: FALSE
A877: esbxxu.cn | B877: benign | C877: 0.94069 | D877: normal | E877: TRUE | F877: legit | G877: TRUE
A878: essaywriter.org | B878: benign | C878: 2.61137 | D878: normal | E878: FALSE | F878: legit | G878: FALSE
A879: etfeeg.cn | B879: benign | C879: 1.426248 | D879: normal | E879: TRUE | F879: legit | G879: TRUE
A880: ethiokw.com | B880: benign | C880: 1.43746 | D880: normal | E880: FALSE | F880: legit | G880: TRUE
A881: etoday.co.kr | B881: benign | C881: 1.417507 | D881: normal | E881: FALSE | F881: legit | G881: FALSE
A882: ets.org | B882: benign | C882: 0.801904 | D882: normal | E882: FALSE | F882: legit | G882: FALSE
... A3001: zzyqrd.com | B3001: benign | C3001: 0.64753 | D3001: normal | E3001: TRUE | F3001: legit | G3001: TRUE

Sheet ex-a_cats
A1: Domains | B1: Verdict | C1: Shannon_Entropy | D1: Shannon_Flag | E1: exp0se (is_dga) | F1: mia_prediction | G1: DGAD: overall flag (is_dga)
A2: 6vlzay.info | B2: evil | C2: 0.754143 | D2: normal | E2: TRUE | F2: legit | G2: TRUE
A3: 95tx6b.info | B3: evil | C3: 0.467676 | D3: suspicious | E3: TRUE | F3: legit | G3: FALSE
A4: aaayfbz.com | B4: evil | C4: 1.309865 | D4: normal | E4: TRUE | F4: legit | G4: TRUE
A5: aaevyjm.com | B5: evil | C5: 1.325812 | D5: normal | E5: TRUE | F5: legit | G5: TRUE
A6: aahrmat.com | B6: evil | C6: 1.720253 | D6: suspicious | E6: TRUE | F6: legit | G6: TRUE
A7: aahrywy.com | B7: evil | C7: 1.270651 | D7: normal | E7: TRUE | F7: legit | G7: TRUE
A8: aayyxpa.com | B8: evil | C8: 1.317883 | D8: normal | E8: TRUE | F8: legit | G8: TRUE
A9: aazdzma.com | B9: evil | C9: 1.386067 | D9: normal | E9: TRUE | F9: legit | G9: TRUE
A10: abmygoh.com | B10: evil | C10: 1.263709 | D10: normal | E10: TRUE | F10: legit | G10: TRUE
A11: abrolwj.com | B11: evil | C11: 1.297167 | D11: normal | E11: TRUE | F11: legit | G11: TRUE
A12: abtlgrb.com | B12: evil | C12: 1.382922 | D12: normal | E12: TRUE | F12: legit | G12: TRUE
A13: abuxud.online | B13: evil | C13: 0.966918 | D13: normal | E13: TRUE | F13: legit | G13: TRUE
... A3001: zzjlgpa.com | B3001: evil | C3001: 0.947011 | D3001: normal | E3001: TRUE | F3001: legit | G3001: TRUE

Sheet ex-b_double
A1: Domains | B1: Verdict | C1: Shannon_Entropy | D1: Shannon_Flag | E1: exp0se (is_dga) | F1: mia_prediction | G1: DGAD: overall flag (is_dga)
A2: 2223.online | B2: evil | C2: 0.141354 | D2: suspicious | E2: FALSE | F2: legit | G2: FALSE
A3: abacat.online | B3: evil | C3: 1.498968 | D3: normal | E3: FALSE | F3: legit | G3: FALSE
A4: aband.business | B4: evil | C4: 1.151381 | D4: normal | E4: FALSE | F4: legit | G4: FALSE
A5: abate.software | B5: evil | C5: 1.307887 | D5: normal | E5: FALSE | F5: legit | G5: FALSE
A6: abdomenmentally.com | B6: evil | C6: 3.413488 | D6: normal | E6: FALSE | F6: legit | G6: FALSE
A7: abnor.business | B7: evil | C7: 1.213177 | D7: normal | E7: FALSE | F7: legit | G7: FALSE
A8: abnormal.associates | B8: evil | C8: 1.901712 | D8: normal | E8: FALSE | F8: legit | G8: FALSE
A9: abnormalpurity.photography | B9: evil | C9: 3.060124 | D9: normal | E9: FALSE | F9: legit | G9: FALSE
A10: abort.shopping | B10: evil | C10: 1.212163 | D10: normal | E10: FALSE | F10: legit | G10: FALSE
A11: abortionconsign.financial | B11: evil | C11: 3.629473 | D11: normal | E11: FALSE | F11: legit | G11: FALSE
A12: abovevertebra.finance | B12: evil | C12: 2.996886 | D12: normal | E12: FALSE | F12: legit | G12: FALSE
A13: abrid.business | B13: evil | C13: 1.111304 | D13: normal | E13: FALSE | F13: legit | G13: FALSE
... A3001: zincpowerful.business | B3001: evil | C3001: 2.31294 | D3001: normal | E3001: FALSE | F3001: legit | G3001: FALSE

Sheet ex-c_pandora
A1: Domains | B1: Verdict | C1: Shannon_Entropy | D1: Shannon_Flag | E1: exp0se (is_dga) | F1: mia_prediction | G1: DGAD: overall flag (is_dga)
A2: amazon.com-custosasmz.top | B2: evil | C2: 2.871675 | D2: normal | E2: FALSE | F2: legit | G2: FALSE
A3: com-customasder.top | B3: evil | C3: 3.294162 | D3: suspicious | E3: FALSE | F3: legit | G3: FALSE
A4: com-custosaczvzc.top | B4: evil | C4: 2.981186 | D4: normal | E4: TRUE | F4: legit | G4: FALSE
A5: com-custosascsa.top | B5: evil | C5: 3.3887 | D5: suspicious | E5: FALSE | F5: legit | G5: FALSE
A6: com-custosascsm.top | B6: evil | C6: 3.256114 | D6: suspicious | E6: FALSE | F6: legit | G6: FALSE
A7: com-custosascsn.top | B7: evil | C7: 3.319572 | D7: suspicious | E7: FALSE | F7: legit | G7: FALSE
A8: com-custosascsx.top | B8: evil | C8: 3.123271 | D8: suspicious | E8: FALSE | F8: legit | G8: FALSE
A9: com-custosascsz.top | B9: evil | C9: 3.136092 | D9: suspicious | E9: FALSE | F9: legit | G9: FALSE
A10: com-trackami.top | B10: evil | C10: 2.561006 | D10: normal | E10: FALSE | F10: legit | G10: FALSE
A11: com-trackanib.top | B11: evil | C11: 2.752401 | D11: normal | E11: FALSE | F11: legit | G11: FALSE
A12: com-trackanic.top | B12: evil | C12: 2.823912 | D12: normal | E12: FALSE | F12: legit | G12: FALSE
A13: com-trackanif.top | B13: evil | C13: 2.721015 | D13: normal | E13: FALSE | F13: legit | G13: FALSE
... A3001: us-usps-zzzzm.xyz | B3001: evil | C3001: 1.685042 | D3001: suspicious | E3001: TRUE | F3001: legit | G3001: FALSE

Sheet ex-d_easy
A1: Domains | B1: Verdict | C1: Shannon_Entropy | D1: Shannon_Flag | E1: exp0se (is_dga) | F1: mia_prediction | G1: DGAD: overall flag (is_dga)
A2: 73-haupt-road.mahabb.ac.in | B2: evil | C2: 1.182348 | D2: normal | E2: FALSE | F2: legit | G2: FALSE
A3: aukuglubuv.cc | B3: evil | C3: 1.594739 | D3: normal | E3: TRUE | F3: legit | G3: TRUE
A4: com.fcu.xin | B4: evil | C4: 0.457132 | D4: normal | E4: FALSE | F4: legit | G4: FALSE
A5: com-auyn.vip | B5: evil | C5: 1.514932 | D5: normal | E5: FALSE | F5: legit | G5: FALSE
A6: com-bfzo.xin | B6: evil | C6: 1.278561 | D6: normal | E6: TRUE | F6: legit | G6: FALSE
A7: com-cenu.xin | B7: evil | C7: 1.626484 | D7: normal | E7: FALSE | F7: legit | G7: FALSE
A8: com-cgkf.xin | B8: evil | C8: 1.239913 | D8: normal | E8: TRUE | F8: legit | G8: FALSE
A9: com-cuyx.xin | B9: evil | C9: 1.207645 | D9: normal | E9: TRUE | F9: legit | G9: FALSE
A10: com-daai.xin | B10: evil | C10: 1.756547 | D10: normal | E10: TRUE | F10: legit | G10: FALSE
A11: com-dmvaws.top | B11: evil | C11: 1.758073 | D11: normal | E11: TRUE | F11: legit | G11: FALSE
A12: com-dmvdm.city | B12: evil | C12: 1.4575 | D12: normal | E12: TRUE | F12: legit | G12: FALSE
A13: com-dmvep.wang | B13: evil | C13: 1.58624 | D13: normal | E13: TRUE | F13: legit | G13: FALSE
... A3001: wsdot-ug-n.wang | B3001: evil | C3001: 1.632851 | D3001: normal | E3001: TRUE | F3001: legit | G3001: FALSE
